<?xml version="1.0" encoding="utf-8" ?>
<odoo>
        <data>


            <!--Convert Default Website in THEME_NAME website-->
            <record id="website.default_website" model="website">
                <field name="name">Website Name</field>
                <field name="domain">domain</field>
                <field name="company_id" ref="base.main_company"/>
                <field name="user_id" ref="base.public_user"/>
                <field name="favicon" type="base64" file="website_base_multi_anz/static/img/favicon.png"/>
                <!--<field name="social_twitter"></field>-->
                <!--<field name="social_facebook"></field>-->
                <!--<field name="social_instagram"></field>-->
                <!--<field name="social_linkedin"></field>-->
                <!--<field name="social_github"></field>-->
                <!--<field name="social_googleplus"></field>-->
                <field name="base_url">http://_______domain_________/</field>
                <field name="email">info@canilike.com</field>
                <field name="phone">111-222-333</field>
            </record>

        </data>
</odoo>